tinycta/__init__.py
tinycta/linalg.py
tinycta/signal.py
tinycta-0.8.7.dist-info/METADATA
tinycta-0.8.7.dist-info/WHEEL
tinycta-0.8.7.dist-info/licenses/LICENSE
tinycta-0.8.7.dist-info/RECORD
