Metadata-Version: 2.4
Name: TinyCTA
Version: 0.8.7
Summary: ...
Project-URL: repository, https://github.com/tschm/tinycta
Author-email: Thomas Schmelzer <thomas.schmelzer@gmail.com>
License-File: LICENSE
Requires-Python: >=3.11
Requires-Dist: numpy>=2.0.0
Requires-Dist: pandas>=2.2.3
